amiga/__init__.py
amiga/__main__.py
amiga/amiga.py
amiga/libs/__init__.py
amiga/libs/analyze.py
amiga/libs/biolog.py
amiga/libs/comm.py
amiga/libs/commands.py
amiga/libs/compare.py
amiga/libs/confidence.py
amiga/libs/config.py
amiga/libs/curve.py
amiga/libs/detail.py
amiga/libs/diauxie.py
amiga/libs/growth.py
amiga/libs/heatmap.py
amiga/libs/interface.py
amiga/libs/kernel.py
amiga/libs/model.py
amiga/libs/normalize.py
amiga/libs/org.py
amiga/libs/params.py
amiga/libs/plot.py
amiga/libs/read.py
amiga/libs/test.py
amiga/libs/thresholds.py
amiga/libs/trim.py
amiga/libs/utils.py
amiga-3.0.4.dist-info/LICENSE.md
amiga-3.0.4.dist-info/METADATA
amiga-3.0.4.dist-info/WHEEL
amiga-3.0.4.dist-info/entry_points.txt
amiga-3.0.4.dist-info/top_level.txt
amiga-3.0.4.dist-info/RECORD
