Metadata-Version: 2.2
Name: amiga
Version: 3.0.4
Summary: Analysis of Microbial Growth Assays
Author-email: Firas Midani <fsm.promotions@gmail.com>
License: GNU GPL v3.0
Project-URL: Homepage, https://github.com/firasmidani/amiga
Project-URL: Documentation, https://firasmidani.github.io/amiga/
Project-URL: Repository, https://github.com/firasmidani/amiga
Project-URL: Issues, https://github.com/firasmidani/amiga/issues
Requires-Python: <3.13.0,>=3.10.0
License-File: LICENSE.md
Requires-Dist: cycler>=0.11.0
Requires-Dist: Cython>=3.0.0
Requires-Dist: decorator>=5.1.0
Requires-Dist: GPy>=1.13.2
Requires-Dist: kiwisolver>=1.3.2
Requires-Dist: matplotlib>=3.5.1
Requires-Dist: numpy>=1.21.0
Requires-Dist: pandas>=1.3.0
Requires-Dist: paramz>=0.9.5
Requires-Dist: pyparsing>=3.0.0
Requires-Dist: python-dateutil>=2.8.2
Requires-Dist: pytz>=2021.3
Requires-Dist: scipy>=1.8.0
Requires-Dist: seaborn>=0.11.2
Requires-Dist: six>=1.16.0
Requires-Dist: tabulate>=0.8.8
